docker_exporter/__init__.py
docker_exporter/client.py
docker_exporter/export.py
docker_exporter/importer.py
docker_exporter/types.py
docker_exporter/utils.py
scripts/export_images.py
scripts/import_images.py
docker_image_exporter-1.0.0.dist-info/METADATA
docker_image_exporter-1.0.0.dist-info/WHEEL
docker_image_exporter-1.0.0.dist-info/entry_points.txt
docker_image_exporter-1.0.0.dist-info/RECORD
