Metadata-Version: 2.4
Name: docker-image-exporter
Version: 1.0.0
Summary: Export and import Docker images between machines
Requires-Python: >=3.13
Requires-Dist: docker>=6.0.0
Requires-Dist: tqdm>=4.65.0
Provides-Extra: dev
Requires-Dist: bpython>=0.24; extra == 'dev'
Requires-Dist: mypy>=1.0.0; extra == 'dev'
Requires-Dist: pytest-cov>=4.0.0; extra == 'dev'
Requires-Dist: pytest>=7.0.0; extra == 'dev'
Requires-Dist: ruff>=0.1.0; extra == 'dev'
Requires-Dist: twine>=4.0.0; extra == 'dev'
Requires-Dist: types-docker>=0.0.0; extra == 'dev'
Requires-Dist: types-tqdm>=0.0.0; extra == 'dev'
